mkdocs_confluence_publisher/__init__.py
mkdocs_confluence_publisher/create_pages.py
mkdocs_confluence_publisher/plugin.py
mkdocs_confluence_publisher/types.py
mkdocs_confluence_publisher/update_page.py
mkdocs_confluence_publisher/upload_attachments.py
mkdocs_confluence_publisher-0.1.2.dist-info/LICENSE
mkdocs_confluence_publisher-0.1.2.dist-info/METADATA
mkdocs_confluence_publisher-0.1.2.dist-info/WHEEL
mkdocs_confluence_publisher-0.1.2.dist-info/entry_points.txt
mkdocs_confluence_publisher-0.1.2.dist-info/top_level.txt
mkdocs_confluence_publisher-0.1.2.dist-info/RECORD
