Metadata-Version: 2.1
Name: mkdocs-confluence-publisher
Version: 0.1.2
Summary: A MkDocs plugin to publish documentation to Confluence
Home-page: https://github.com/johnny/mkdocs-confluence-publisher
Author: Jonas von Andrian
Author-email: j.andrianmueller@outlook.com
License: Apache License 2.0
Project-URL: Bug Tracker, https://github.com/johnny/mkdocs-confluence-publisher/issues
Keywords: mkdocs confluence documentation
Classifier: Development Status :: 3 - Alpha
Classifier: Intended Audience :: Developers
Classifier: Topic :: Software Development :: Documentation
Classifier: Programming Language :: Python :: 3
Classifier: Programming Language :: Python :: 3.8
Classifier: Programming Language :: Python :: 3.9
Classifier: Programming Language :: Python :: 3.10
Classifier: Programming Language :: Python :: 3.11
Classifier: License :: OSI Approved :: Apache Software License
Classifier: Operating System :: OS Independent
Requires-Python: >=3.8
License-File: LICENSE
Requires-Dist: mkdocs>=1.0
Requires-Dist: atlassian-python-api>=3.14.0
Requires-Dist: mistune
Requires-Dist: md2cf
Requires-Dist: python-dotenv
